rydopt/__init__.py
rydopt/characterization/__init__.py
rydopt/characterization/gate_performance.py
rydopt/characterization/plot_optimization_history.py
rydopt/characterization/plot_pulse.py
rydopt/characterization/plot_spectrum.py
rydopt/characterization/qutip_helpers/qutip_four_qubit_gate_pyramidal.py
rydopt/characterization/qutip_helpers/qutip_simulation.py
rydopt/characterization/qutip_helpers/qutip_three_qubit_gate_isosceles.py
rydopt/characterization/qutip_helpers/qutip_two_qubit_gate.py
rydopt/gates/__init__.py
rydopt/gates/four_qubit_gate_pyramidal.py
rydopt/gates/subsystem_hamiltonians.py
rydopt/gates/three_qubit_gate_isosceles.py
rydopt/gates/two_qubit_gate.py
rydopt/optimization/__init__.py
rydopt/optimization/optimize.py
rydopt/protocols.py
rydopt/pulses/__init__.py
rydopt/pulses/general_pulse_ansatz_functions.py
rydopt/pulses/pulse_ansatz.py
rydopt/pulses/softbox_pulse_ansatz_functions.py
rydopt/simulation/__init__.py
rydopt/simulation/evolve.py
rydopt/simulation/fidelity.py
rydopt/simulation/rydberg_time.py
rydopt/types.py
rydopt-0.2.0.dist-info/WHEEL
rydopt-0.2.0.dist-info/METADATA
rydopt-0.2.0.dist-info/RECORD
