Metadata-Version: 2.3
Name: RydOpt
Version: 0.2.0
Summary: Multiqubit Rydberg Gate Optimizer
Author: David F. Locher, Sebastian Weber, Jakob Holschbach
License: MIT License
Classifier: Intended Audience :: Science/Research
Classifier: License :: OSI Approved :: MIT License
Classifier: Operating System :: MacOS
Classifier: Operating System :: Microsoft :: Windows
Classifier: Operating System :: POSIX :: Linux
Classifier: Programming Language :: Python
Classifier: Programming Language :: Python :: 3
Classifier: Programming Language :: Python :: 3 :: Only
Classifier: Programming Language :: Python :: 3.10
Classifier: Programming Language :: Python :: 3.11
Classifier: Programming Language :: Python :: 3.12
Classifier: Programming Language :: Python :: 3.13
Classifier: Programming Language :: Python :: Implementation :: CPython
Classifier: Topic :: Scientific/Engineering
Classifier: Topic :: Scientific/Engineering :: Physics
Classifier: Topic :: Scientific/Engineering :: Quantum Computing
Requires-Dist: diffrax>=0.5.0
Requires-Dist: jax>=0.4.28
Requires-Dist: jaxlib>=0.4.28
Requires-Dist: matplotlib>=3.9.0
Requires-Dist: numpy>=2.0.2
Requires-Dist: optax>=0.2.2
Requires-Dist: qutip>=5.1.0
Requires-Dist: tqdm>=4.65.0
Requires-Dist: typing-extensions>=4.15.0
Requires-Dist: jax[cuda12]>=0.4.28 ; extra == 'cuda12'
Requires-Dist: pytest>=8.4.2 ; extra == 'dev'
Requires-Dist: sphinx==8.1.3 ; extra == 'dev'
Requires-Dist: sphinx-rtd-theme>=3.0.2 ; extra == 'dev'
Requires-Dist: sphinx-autobuild>=2024.10.3 ; extra == 'dev'
Requires-Dist: sphinxcontrib-napoleon>=0.7 ; extra == 'dev'
Requires-Dist: nbsphinx>=0.9.7 ; extra == 'dev'
Requires-Dist: sphinx-tabs>=3.4.7 ; extra == 'dev'
Requires-Dist: sphinx-copybutton>=0.5.2 ; extra == 'dev'
Requires-Dist: notebook>=7.5.0 ; extra == 'dev'
Requires-Dist: ipykernel>=7.1.0 ; extra == 'dev'
Requires-Dist: ipywidgets>=8.1.8 ; extra == 'dev'
Requires-Dist: nbmake>=1.5.5 ; extra == 'dev'
Maintainer: Sebastian Weber, David F. Locher
Maintainer-email: Sebastian Weber <seweber@posteo.de>, David F. Locher <david.locher@rwth-aachen.de>
Requires-Python: >=3.10
Provides-Extra: cuda12
Provides-Extra: dev
